airflow_kjo/__init__.py
airflow_kjo/__version__
airflow_kjo/kubernetes_job_launcher.py
airflow_kjo/kubernetes_job_operator.py
airflow_kjo/kubernetes_util.py
airflow_kube_job_operator-0.2.5.dist-info/LICENSE
airflow_kube_job_operator-0.2.5.dist-info/METADATA
airflow_kube_job_operator-0.2.5.dist-info/WHEEL
airflow_kube_job_operator-0.2.5.dist-info/top_level.txt
airflow_kube_job_operator-0.2.5.dist-info/RECORD
