Metadata-Version: 2.1
Name: airflow-kube-job-operator
Version: 0.2.5
Summary: Kubernetes job operator for Airflow
Home-page: UNKNOWN
Author: EliMor
Author-email: elimor.github@gmail.com
License: Apache License 2.0
Platform: UNKNOWN
Classifier: Programming Language :: Python :: 3.6
Classifier: Programming Language :: Python :: 3.7
Classifier: Programming Language :: Python :: 3.8
Classifier: Programming Language :: Python :: 3.9
Classifier: License :: OSI Approved :: Apache Software License
License-File: LICENSE
Requires-Dist: apache-airflow (>=2.0.0)
Requires-Dist: kubernetes (>=11.0.0)
Requires-Dist: Jinja2 (>=2.11.3)
Provides-Extra: tests
Requires-Dist: pytest ; extra == 'tests'
